yalafi_ls/__init__.py
yalafi_ls/__main__.py
yalafi_ls/server.py
yalafi_ls-0.0.1.dist-info/LICENSE
yalafi_ls-0.0.1.dist-info/METADATA
yalafi_ls-0.0.1.dist-info/WHEEL
yalafi_ls-0.0.1.dist-info/top_level.txt
yalafi_ls-0.0.1.dist-info/RECORD
