Metadata-Version: 2.1
Name: yalafi-ls
Version: 0.0.1
Summary: YaLafi LSP server for spellchecking LaTeX documents
Author: torik42
Project-URL: Homepage, https://github.com/torik42/YaLafi-LS
Project-URL: Changelog, https://github.com/torik42/YaLafi-LS/blob/main/HISTORY.md
Project-URL: Documentation, https://github.com/torik42/YaLafi-LS
Project-URL: Issue Tracker, https://github.com/torik42/YaLafi-LS/issues
Classifier: Development Status :: 3 - Alpha
Classifier: Programming Language :: Python :: 3
Classifier: License :: OSI Approved :: GNU General Public License v3 (GPLv3)
Classifier: Operating System :: OS Independent
Classifier: Topic :: Text Processing :: Markup :: LaTeX
Classifier: Topic :: Text Editors :: Integrated Development Environments (IDE)
License-File: LICENSE
Requires-Dist: lsprotocol
Requires-Dist: pygls (~=1.0)
Requires-Dist: yalafi
